pocal/__init__.py
pocal/thinfilms.py
pocal-2.236.dist-info/LICENSE.txt
pocal-2.236.dist-info/METADATA
pocal-2.236.dist-info/WHEEL
pocal-2.236.dist-info/top_level.txt
pocal-2.236.dist-info/RECORD
