Metadata-Version: 2.1
Name: pocal
Version: 2.236
Summary: POCAL (Python Optical Coating Analysis Library)
Home-page: UNKNOWN
License: UNKNOWN
Platform: UNKNOWN
Classifier: Programming Language :: Python
Classifier: License :: OSI Approved :: MIT License
Classifier: Topic :: Scientific/Engineering :: Physics
